webants/__init__.py
webants/downloader.py
webants/parser.py
webants/scheduler.py
webants/spider.py
webants/libs/__init__.py
webants/libs/exceptions.py
webants/libs/extractor.py
webants/libs/item.py
webants/libs/middleware.py
webants/libs/request.py
webants/libs/response.py
webants/libs/result.py
webants/utils/__init__.py
webants/utils/logger.py
webants/utils/login.py
webants/utils/misc.py
webants/utils/statistic.py
webants/utils/url.py
webants-0.0.1.dist-info/METADATA
webants-0.0.1.dist-info/WHEEL
webants-0.0.1.dist-info/top_level.txt
webants-0.0.1.dist-info/RECORD
